metku/__init__.py
metku/log_to_file.py
metku/cost/__init__.py
metku/cost/cost_calculation.py
metku/cost/cost_data.py
metku/cost/workshop.py
metku/design/__init__.py
metku/design/cross_section.py
metku/design/steel_section.py
metku/eurocodes/__init__.py
metku/eurocodes/en1991/__init__.py
metku/eurocodes/en1991/en1991.py
metku/eurocodes/en1991/en1991_1_4.py
metku/eurocodes/en1991/loadIDs.py
metku/eurocodes/en1992/__init__.py
metku/eurocodes/en1992/constants.py
metku/eurocodes/en1992/en1992_1_1.py
metku/eurocodes/en1993/__init__.py
metku/eurocodes/en1993/constants.py
metku/eurocodes/en1993/en1993_1_1.py
metku/eurocodes/en1993/en1993_1_2.py
metku/eurocodes/en1993/en1993_1_5.py
metku/eurocodes/en1993/en1993_1_3/__init__.py
metku/eurocodes/en1993/en1993_1_3/cf_profs.py
metku/eurocodes/en1993/en1993_1_3/en1993_1_3.py
metku/eurocodes/en1993/en1993_1_3/open_prof.py
metku/eurocodes/en1993/en1993_1_3/trapezoidal.py
metku/eurocodes/en1993/en1993_1_8/__init__.py
metku/eurocodes/en1993/en1993_1_8/component_method.py
metku/eurocodes/en1993/en1993_1_8/en1993_1_8.py
metku/eurocodes/en1993/en1993_1_8/rhs_joints.py
metku/eurocodes/en1994/__init__.py
metku/eurocodes/en1994/constants.py
metku/eurocodes/en1994/en1994_1_1.py
metku/eurocodes/en1995/__init__.py
metku/eurocodes/en1995/constants.py
metku/eurocodes/en1995/en1995_1_1.py
metku/eurocodes/en1995/en1995_1_2.py
metku/eurocodes/en1995/fire_protection.py
metku/examples/__init__.py
metku/examples/beam.py
metku/examples/beam_optimization.py
metku/examples/example_raami.py
metku/examples/frame_optimization.py
metku/examples/mathematical_optimization.py
metku/examples/raami_plane_truss_example.py
metku/examples/threebartruss_optimization.py
metku/examples/trussed_frame.py
metku/frame2d/__init__.py
metku/frame2d/frame.py
metku/frame2d/frame2d.py
metku/frame2d/frame2d_test.py
metku/frame2d/frame_example.py
metku/frame2d/frameoptimizer.py
metku/frame2d/geometry.py
metku/frame2d/loads.py
metku/frame2d/materials.py
metku/frame2d/member.py
metku-0.1.34.dist-info/LICENSE
metku-0.1.34.dist-info/METADATA
metku-0.1.34.dist-info/WHEEL
metku-0.1.34.dist-info/top_level.txt
metku-0.1.34.dist-info/RECORD
