Metadata-Version: 2.1
Name: metku
Version: 0.1.34
Summary: Module for structural analysis and optimization
Home-page: https://github.com/kuisidu/metku
Author: Kristo Mela, Jaakko Huusko, Viktor Haimi
License: MIT
Classifier: Development Status :: 4 - Beta
Classifier: Programming Language :: Python :: 3
Classifier: License :: OSI Approved :: MIT License
Classifier: Operating System :: OS Independent
Classifier: Programming Language :: Python :: 3.9
Classifier: Programming Language :: Python :: 3.10
Classifier: Intended Audience :: Education
Classifier: Intended Audience :: Science/Research
Requires-Python: >=3.9
License-File: LICENSE
Requires-Dist: setuptools>=65.5.1
Requires-Dist: treelib>=1.6.1
Requires-Dist: deap>=1.3.3
Requires-Dist: numpy>=2.0.1
Requires-Dist: matplotlib>=3.9.1
Requires-Dist: pandas>=2.2.2
Requires-Dist: scipy>=1.14.0
Requires-Dist: ortools>=9.10.4067
Requires-Dist: nh3~=0.2.18
Requires-Dist: pillow~=10.4.0
Requires-Dist: pip~=24.2
Requires-Dist: wheel~=0.44.0
Requires-Dist: docutils~=0.21.2
Requires-Dist: pytz~=2024.2
Requires-Dist: rich~=13.7.1
Requires-Dist: Pygments~=2.18.0
Requires-Dist: zipp~=3.20.0
Requires-Dist: importlib_metadata~=8.3.0
Requires-Dist: pyproject_hooks~=1.1.0
Requires-Dist: build~=1.2.2
Requires-Dist: mdurl~=0.1.2
Requires-Dist: colorama~=0.4.6
Requires-Dist: metku~=0.1.20
Requires-Dist: pytest~=8.3.3
Requires-Dist: twine~=5.1.1
Requires-Dist: keyring~=25.3.0
Requires-Dist: readme_renderer~=44.0
Requires-Dist: requests~=2.32.3
Requires-Dist: rfc3986~=2.0.0
Requires-Dist: pkginfo~=1.10.0
Requires-Dist: urllib3~=2.2.2
Requires-Dist: python-dateutil~=2.9.0.post0
Requires-Dist: pluggy~=1.5.0
Requires-Dist: iniconfig~=2.0.0
Requires-Dist: certifi~=2024.7.4
Requires-Dist: immutabledict~=4.2.0
Requires-Dist: idna~=3.7
Requires-Dist: six~=1.16.0
Requires-Dist: contourpy~=1.3.0
Requires-Dist: fonttools~=4.53.1
Requires-Dist: pyparsing~=3.1.4
Requires-Dist: cycler~=0.12.1
Requires-Dist: packaging~=24.1
Requires-Dist: kiwisolver~=1.4.7
